{
    "name": "beyond20",
    "title": "Beyond20 companion module",
    "description": "This module allows the Beyond20 rolls to display properly in the main FVTT window and for other players who do not have Beyond20 installed",
    "version": "1.2.1",
    "author": "KaKaRoTo",
    "systems": ["dnd5e_paw"],
    "scripts": ["./beyond20.js"],
    "styles": ["./beyond20.css"],
    "packs": [],
    "url": "https://https://github.com/TheStonedGuest/Beyond20-Foundry-PAW",
    "manifest": "https://https://github.com/TheStonedGuest/Beyond20-Foundry-PAW/releases/download/1.2/module.json",
    "download": "https://https://github.com/TheStonedGuest/Beyond20-Foundry-PAW/releases/download/1.2/Beyond20-Foundry-PAW.zip",
    "minimumCoreVersion": "0.6.0",
    "compatibleCoreVersion": "0.7.10"
}
